pylzf/__init__.py
pylzf/backends/__init__.py
pylzf/backends/cffi/__init__.py
pylzf/backends/cffi/_lzf.pypy37-pp73-x86_64-linux-gnu.so
pylzf/backends/cffi/build.py
pylzf/backends/cython/__init__.py
pylzf/backends/cython/_lzf.c
pylzf/backends/cython/_lzf.pypy37-pp73-x86_64-linux-gnu.so
pylzf/backends/cython/_lzf.pyx
pylzf/backends/cython/lzf.pxd
pylzf-0.1.1.dist-info/METADATA
pylzf-0.1.1.dist-info/WHEEL
pylzf-0.1.1.dist-info/top_level.txt
pylzf-0.1.1.dist-info/RECORD
