Metadata-Version: 2.1
Name: pylzf
Version: 0.1.1
Summary: LibLZF is a very small data compression library
Home-page: https://github.com/synodriver/pylzf
Author: synodriver
Author-email: diguohuangjiajinweijun@gmail.com
License: BSD
Keywords: compress,decompress
Classifier: Development Status :: 4 - Beta
Classifier: Operating System :: OS Independent
Classifier: License :: OSI Approved :: BSD License
Classifier: Programming Language :: C
Classifier: Programming Language :: Cython
Classifier: Programming Language :: Python
Classifier: Programming Language :: Python :: 3.6
Classifier: Programming Language :: Python :: 3.7
Classifier: Programming Language :: Python :: 3.8
Classifier: Programming Language :: Python :: 3.9
Classifier: Programming Language :: Python :: 3.10
Classifier: Programming Language :: Python :: Implementation :: CPython
Classifier: Programming Language :: Python :: Implementation :: PyPy
Requires-Python: >=3.6
